LICENSE.txt
setup.cfg
setup.py
umangchaudhary/__init__.py
umangchaudhary/api.py
umangchaudhary.egg-info/PKG-INFO
umangchaudhary.egg-info/SOURCES.txt
umangchaudhary.egg-info/dependency_links.txt
umangchaudhary.egg-info/top_level.txt